certbot_dns_csc/__init__.py
certbot_dns_csc/csc_client.py
certbot_dns_csc/dns_csc.py
certbot_dns_csc-1.0.1.dist-info/licenses/LICENSE
tests/__init__.py
tests/test_dns_csc.py
certbot_dns_csc-1.0.1.dist-info/METADATA
certbot_dns_csc-1.0.1.dist-info/WHEEL
certbot_dns_csc-1.0.1.dist-info/entry_points.txt
certbot_dns_csc-1.0.1.dist-info/top_level.txt
certbot_dns_csc-1.0.1.dist-info/RECORD
