Metadata-Version: 2.4
Name: certbot-dns-csc
Version: 1.0.1
Summary: CSC Global Domain Manager DNS Authenticator plugin for Certbot
Home-page: https://github.com/EnginEken/certbot-dns-csc
Author: Engin Eken
Author-email: e.eken@outlook.com
Project-URL: Bug Tracker, https://github.com/EnginEken/certbot-dns-csc/issues
Classifier: Development Status :: 4 - Beta
Classifier: Environment :: Plugins
Classifier: Intended Audience :: System Administrators
Classifier: License :: OSI Approved :: Apache Software License
Classifier: Operating System :: POSIX :: Linux
Classifier: Programming Language :: Python
Classifier: Programming Language :: Python :: 3
Classifier: Programming Language :: Python :: 3.6
Classifier: Programming Language :: Python :: 3.7
Classifier: Programming Language :: Python :: 3.8
Classifier: Programming Language :: Python :: 3.9
Classifier: Programming Language :: Python :: 3.10
Classifier: Programming Language :: Python :: 3.11
Classifier: Topic :: Internet :: WWW/HTTP
Classifier: Topic :: Security
Classifier: Topic :: System :: Installation/Setup
Classifier: Topic :: System :: Networking
Classifier: Topic :: System :: Systems Administration
Classifier: Topic :: Utilities
Requires-Python: >=3.6
License-File: LICENSE
Requires-Dist: acme>=0.31.0
Requires-Dist: certbot>=0.31.0
Requires-Dist: requests>=2.20.0
Requires-Dist: setuptools
Requires-Dist: zope.interface
Provides-Extra: dev
Requires-Dist: pytest>=3.0.0; extra == "dev"
Requires-Dist: pytest-cov; extra == "dev"
Requires-Dist: responses>=0.9.0; extra == "dev"
Dynamic: author
Dynamic: author-email
Dynamic: classifier
Dynamic: description
Dynamic: description-content-type
Dynamic: home-page
Dynamic: license-file
Dynamic: project-url
Dynamic: provides-extra
Dynamic: requires-dist
Dynamic: requires-python
Dynamic: summary
